cc/xboxcontroller/__init__.py
cc/xboxcontroller/xboxcontroller.py
cc.xboxcontroller-2024.9.2.dist-info/LICENSE
cc.xboxcontroller-2024.9.2.dist-info/METADATA
cc.xboxcontroller-2024.9.2.dist-info/WHEEL
cc.xboxcontroller-2024.9.2.dist-info/top_level.txt
cc.xboxcontroller-2024.9.2.dist-info/RECORD
