Metadata-Version: 2.1
Name: cc.xboxcontroller
Version: 2024.9.2
Summary: Getting input from Microsoft XBox 360 controllers via the XInput library on Windows.
Home-page: https://github.com/uncertainty-cc/XboxController-Python
Author: Uncertainty.
Author-email: t_k_233@outlook.email
Classifier: Programming Language :: Python :: 3
Classifier: License :: OSI Approved :: MIT License
Classifier: Operating System :: OS Independent
Requires-Python: >=3.8
License-File: LICENSE
Requires-Dist: pyglet
